{
  "id": "616d077f-fecc-8001-8007-c46a44d4bce4",
  "name": "Atomics graphs",
  "type": "text",
  "x": 1363,
  "y": 1104,
  "width": 94,
  "height": 12,
  "rotation": 0,
  "selrect": {
    "x": 1363,
    "y": 1104,
    "width": 94,
    "height": 12,
    "x1": 1363,
    "y1": 1104,
    "x2": 1457,
    "y2": 1116
  },
  "points": [
    {
      "x": 1363,
      "y": 1104
    },
    {
      "x": 1457,
      "y": 1104
    },
    {
      "x": 1457,
      "y": 1116
    },
    {
      "x": 1363,
      "y": 1116
    }
  ],
  "transform": {
    "a": 1.0,
    "b": 0.0,
    "c": 0.0,
    "d": 1.0,
    "e": 0.0,
    "f": 0.0
  },
  "transformInverse": {
    "a": 1.0,
    "b": 0.0,
    "c": 0.0,
    "d": 1.0,
    "e": 0.0,
    "f": 0.0
  },
  "parentId": "616d077f-fecc-8001-8007-c46a44d44407",
  "frameId": "616d077f-fecc-8001-8007-c46a44d44407",
  "flipX": null,
  "flipY": null,
  "growType": "fixed",
  "content": {
    "type": "root",
    "children": [
      {
        "type": "paragraph-set",
        "children": [
          {
            "lineHeight": "1.2",
            "fontStyle": "normal",
            "children": [
              {
                "lineHeight": "1.2",
                "fontStyle": "normal",
                "textTransform": "capitalize",
                "textAlign": "left",
                "fontId": "sourcesanspro",
                "fontSize": "12",
                "fontWeight": "400",
                "textDirection": "ltr",
                "fontVariantId": "regular",
                "textDecoration": "none",
                "letterSpacing": "0",
                "fills": [
                  {
                    "fillColor": "#000000",
                    "fillOpacity": 1
                  }
                ],
                "fontFamily": "sourcesanspro",
                "text": "Atomics graphs"
              }
            ],
            "textTransform": "capitalize",
            "textAlign": "left",
            "fontId": "sourcesanspro",
            "key": "fik5f",
            "fontSize": "12",
            "fontWeight": "400",
            "textDirection": "ltr",
            "type": "paragraph",
            "fontVariantId": "regular",
            "textDecoration": "none",
            "letterSpacing": "0",
            "fills": [
              {
                "fillColor": "#000000",
                "fillOpacity": 1
              }
            ],
            "fontFamily": "sourcesanspro"
          }
        ]
      }
    ]
  },
  "hideInViewer": false,
  "positionData": [
    {
      "x": 1363,
      "y": 1119.6999969482422,
      "width": 78.21665954589844,
      "height": 17,
      "x1": 0,
      "y1": -1.3000030517578125,
      "x2": 78.21665954589844,
      "y2": 15.699996948242188,
      "fontStyle": "normal",
      "textTransform": "capitalize",
      "fontSize": "12px",
      "fontWeight": "400",
      "textDecoration": "none",
      "letterSpacing": "normal",
      "fills": [
        {
          "fillColor": "#000000",
          "fillOpacity": 1
        }
      ],
      "direction": "ltr",
      "fontFamily": "\"sourcesanspro\"",
      "text": "Atomics graphs"
    }
  ],
  "strokes": [],
  "blocked": false,
  "fills": [],
  "pageId": "91eb1cb6-b8ef-80d8-8007-bfd3c3dddd22"
}